src/decision_unit.v
module decision_unit(

    input wire contamination,

    output wire alarm

);

assign alarm = contamination;

endmodule

rtl/ai_classifier.v
module ai_classifier(

    input wire clk,
    input wire rst,

    input wire [7:0] lead,
    input wire [7:0] arsenic,
    input wire [7:0] cadmium,
    input wire [7:0] chromium,
    input wire [7:0] mercury,

    output reg contamination

);

parameter signed W_LEAD      = 536;
parameter signed W_ARSENIC   = 446;
parameter signed W_CADMIUM   = 266;
parameter signed W_CHROMIUM  = 357;
parameter signed W_MERCURY   = 178;
parameter signed BIAS        = -213817;

reg signed [31:0] score;

always @(posedge clk or posedge rst) begin

    if (rst) begin
        score <= 32'sd0;
        contamination <= 1'b0;
    end
    else begin

        score <=
            lead      * W_LEAD +
            arsenic   * W_ARSENIC +
            cadmium   * W_CADMIUM +
            chromium  * W_CHROMIUM +
            mercury   * W_MERCURY +
            BIAS;

        contamination <= (score >= 0);

    end

end

endmodule

rtl/feature_extractor.v
module feature_extractor(

    input wire clk,
    input wire rst,

    input wire [7:0] lead,
    input wire [7:0] arsenic,
    input wire [7:0] cadmium,
    input wire [7:0] chromium,
    input wire [7:0] mercury,

    output reg [10:0] total,
    output reg [9:0] average,
    output reg [7:0] maximum

);

wire [10:0] sum;

assign sum = lead + arsenic + cadmium + chromium + mercury;

always @(posedge clk or posedge rst) begin

    if (rst) begin
        total   <= 11'd0;
        average <= 10'd0;
        maximum <= 8'd0;
    end
    else begin
        total   <= sum;
        average <= sum / 5;

        if ((lead >= arsenic) &&
            (lead >= cadmium) &&
            (lead >= chromium) &&
            (lead >= mercury))
            maximum <= lead;
        else if ((arsenic >= cadmium) &&
                 (arsenic >= chromium) &&
                 (arsenic >= mercury))
            maximum <= arsenic;
        else if ((cadmium >= chromium) &&
                 (cadmium >= mercury))
            maximum <= cadmium;
        else if (chromium >= mercury)
            maximum <= chromium;
        else
            maximum <= mercury;
    end

end

endmodule

rtl/preprocessing.v
module preprocessing(

    input wire clk,
    input wire rst,

    input wire [7:0] lead_in,
    input wire [7:0] arsenic_in,
    input wire [7:0] cadmium_in,
    input wire [7:0] chromium_in,
    input wire [7:0] mercury_in,

    output reg [7:0] lead_norm,
    output reg [7:0] arsenic_norm,
    output reg [7:0] cadmium_norm,
    output reg [7:0] chromium_norm,
    output reg [7:0] mercury_norm

);

always @(posedge clk or posedge rst) begin

    if (rst) begin
        lead_norm <= 8'd0;
        arsenic_norm <= 8'd0;
        cadmium_norm <= 8'd0;
        chromium_norm <= 8'd0;
        mercury_norm <= 8'd0;
    end
    else begin
        // Placeholder normalization (identity mapping)
        lead_norm <= lead_in;
        arsenic_norm <= arsenic_in;
        cadmium_norm <= cadmium_in;
        chromium_norm <= chromium_in;
        mercury_norm <= mercury_in;
    end

end

endmodule

src/sensor_interface.v
module sensor_interface (
    input wire clk,
    input wire rst,

    // Heavy metal sensor inputs
    input wire [7:0] lead_sensor,
    input wire [7:0] arsenic_sensor,
    input wire [7:0] cadmium_sensor,
    input wire [7:0] chromium_sensor,
    input wire [7:0] mercury_sensor,

    // Registered outputs
    output reg [7:0] lead_data,
    output reg [7:0] arsenic_data,
    output reg [7:0] cadmium_data,
    output reg [7:0] chromium_data,
    output reg [7:0] mercury_data
);

always @(posedge clk or posedge rst) begin
    if (rst) begin
        lead_data     <= 8'd0;
        arsenic_data  <= 8'd0;
        cadmium_data  <= 8'd0;
        chromium_data <= 8'd0;
        mercury_data  <= 8'd0;
    end
    else begin
        lead_data     <= lead_sensor;
        arsenic_data  <= arsenic_sensor;
        cadmium_data  <= cadmium_sensor;
        chromium_data <= chromium_sensor;
        mercury_data  <= mercury_sensor;
    end
end

endmodule

rtl/water_chip_ai.v
module water_chip_ai(

    input wire clk,
    input wire rst,

    input wire [7:0] lead_sensor,
    input wire [7:0] arsenic_sensor,
    input wire [7:0] cadmium_sensor,
    input wire [7:0] chromium_sensor,
    input wire [7:0] mercury_sensor,

    output wire contamination_alarm

);

wire [7:0] lead_data;
wire [7:0] arsenic_data;
wire [7:0] cadmium_data;
wire [7:0] chromium_data;
wire [7:0] mercury_data;

wire [7:0] lead_norm;
wire [7:0] arsenic_norm;
wire [7:0] cadmium_norm;
wire [7:0] chromium_norm;
wire [7:0] mercury_norm;

wire [10:0] total;
wire [9:0] average;
wire [7:0] maximum;

wire contamination;

// Sensor Interface
sensor_interface sensor_if(
    .clk(clk),
    .rst(rst),
    .lead_sensor(lead_sensor),
    .arsenic_sensor(arsenic_sensor),
    .cadmium_sensor(cadmium_sensor),
    .chromium_sensor(chromium_sensor),
    .mercury_sensor(mercury_sensor),
    .lead_data(lead_data),
    .arsenic_data(arsenic_data),
    .cadmium_data(cadmium_data),
    .chromium_data(chromium_data),
    .mercury_data(mercury_data)
);

// Preprocessing
preprocessing prep(
    .clk(clk),
    .rst(rst),
    .lead_in(lead_data),
    .arsenic_in(arsenic_data),
    .cadmium_in(cadmium_data),
    .chromium_in(chromium_data),
    .mercury_in(mercury_data),
    .lead_norm(lead_norm),
    .arsenic_norm(arsenic_norm),
    .cadmium_norm(cadmium_norm),
    .chromium_norm(chromium_norm),
    .mercury_norm(mercury_norm)
);

// Feature Extraction
feature_extractor feature(
    .clk(clk),
    .rst(rst),
    .lead(lead_norm),
    .arsenic(arsenic_norm),
    .cadmium(cadmium_norm),
    .chromium(chromium_norm),
    .mercury(mercury_norm),
    .total(total),
    .average(average),
    .maximum(maximum)
);

// AI Classifier
ai_classifier ai(
    .clk(clk),
    .rst(rst),
    .lead(lead_norm),
    .arsenic(arsenic_norm),
    .cadmium(cadmium_norm),
    .chromium(chromium_norm),
    .mercury(mercury_norm),
    .contamination(contamination)
);

// Decision Unit
decision_unit decision(
    .contamination(contamination),
    .alarm(contamination_alarm)
);

endmodule

tb/tb_water_chip_ai.v
`timescale 1ns/1ps

module tb_water_chip_ai;

reg clk;
reg rst;

reg [7:0] lead_sensor;
reg [7:0] arsenic_sensor;
reg [7:0] cadmium_sensor;
reg [7:0] chromium_sensor;
reg [7:0] mercury_sensor;

wire contamination_alarm;

// Device Under Test
water_chip_ai dut (
    .clk(clk),
    .rst(rst),
    .lead_sensor(lead_sensor),
    .arsenic_sensor(arsenic_sensor),
    .cadmium_sensor(cadmium_sensor),
    .chromium_sensor(chromium_sensor),
    .mercury_sensor(mercury_sensor),
    .contamination_alarm(contamination_alarm)
);

// Clock
always #5 clk = ~clk;

initial begin

    $dumpfile("water_chip_ai.vcd");
    $dumpvars(0, tb_water_chip_ai);

    clk = 0;
    rst = 1;

    lead_sensor = 0;
    arsenic_sensor = 0;
    cadmium_sensor = 0;
    chromium_sensor = 0;
    mercury_sensor = 0;

    #20;
    rst = 0;

    // Safe water
    lead_sensor = 10;
    arsenic_sensor = 8;
    cadmium_sensor = 5;
    chromium_sensor = 7;
    mercury_sensor = 6;

    #50;

    // Contaminated water
    lead_sensor = 180;
    arsenic_sensor = 150;
    cadmium_sensor = 120;
    chromium_sensor = 160;
    mercury_sensor = 140;

    #100;

    $finish;

end

endmodule

water_chip_ai.vcd
$date
	Mon Jul  6 22:50:35 2026
$end
$version
	Icarus Verilog
$end
$timescale
	1ps
$end
$scope module tb_water_chip_ai $end
$var wire 1 ! contamination_alarm $end
$var reg 8 " arsenic_sensor [7:0] $end
$var reg 8 # cadmium_sensor [7:0] $end
$var reg 8 $ chromium_sensor [7:0] $end
$var reg 1 % clk $end
$var reg 8 & lead_sensor [7:0] $end
$var reg 8 ' mercury_sensor [7:0] $end
$var reg 1 ( rst $end
$scope module dut $end
$var wire 8 ) arsenic_sensor [7:0] $end
$var wire 8 * cadmium_sensor [7:0] $end
$var wire 8 + chromium_sensor [7:0] $end
$var wire 1 % clk $end
$var wire 8 , lead_sensor [7:0] $end
$var wire 8 - mercury_sensor [7:0] $end
$var wire 1 ( rst $end
$var wire 11 . total [10:0] $end
$var wire 8 / mercury_norm [7:0] $end
$var wire 8 0 mercury_data [7:0] $end
$var wire 8 1 maximum [7:0] $end
$var wire 8 2 lead_norm [7:0] $end
$var wire 8 3 lead_data [7:0] $end
$var wire 1 ! contamination_alarm $end
$var wire 1 4 contamination $end
$var wire 8 5 chromium_norm [7:0] $end
$var wire 8 6 chromium_data [7:0] $end
$var wire 8 7 cadmium_norm [7:0] $end
$var wire 8 8 cadmium_data [7:0] $end
$var wire 10 9 average [9:0] $end
$var wire 8 : arsenic_norm [7:0] $end
$var wire 8 ; arsenic_data [7:0] $end
$scope module ai $end
$var wire 1 % clk $end
$var wire 1 ( rst $end
$var wire 8 < mercury [7:0] $end
$var wire 8 = lead [7:0] $end
$var wire 8 > chromium [7:0] $end
$var wire 8 ? cadmium [7:0] $end
$var wire 8 @ arsenic [7:0] $end
$var parameter 32 A BIAS $end
$var parameter 32 B W_ARSENIC $end
$var parameter 32 C W_CADMIUM $end
$var parameter 32 D W_CHROMIUM $end
$var parameter 32 E W_LEAD $end
$var parameter 32 F W_MERCURY $end
$var reg 1 4 contamination $end
$var reg 32 G score [31:0] $end
$upscope $end
$scope module decision $end
$var wire 1 ! alarm $end
$var wire 1 4 contamination $end
$upscope $end
$scope module feature $end
$var wire 1 % clk $end
$var wire 1 ( rst $end
$var wire 11 H sum [10:0] $end
$var wire 8 I mercury [7:0] $end
$var wire 8 J lead [7:0] $end
$var wire 8 K chromium [7:0] $end
$var wire 8 L cadmium [7:0] $end
$var wire 8 M arsenic [7:0] $end
$var reg 10 N average [9:0] $end
$var reg 8 O maximum [7:0] $end
$var reg 11 P total [10:0] $end
$upscope $end
$scope module prep $end
$var wire 1 % clk $end
$var wire 1 ( rst $end
$var wire 8 Q mercury_in [7:0] $end
$var wire 8 R lead_in [7:0] $end
$var wire 8 S chromium_in [7:0] $end
$var wire 8 T cadmium_in [7:0] $end
$var wire 8 U arsenic_in [7:0] $end
$var reg 8 V arsenic_norm [7:0] $end
$var reg 8 W cadmium_norm [7:0] $end
$var reg 8 X chromium_norm [7:0] $end
$var reg 8 Y lead_norm [7:0] $end
$var reg 8 Z mercury_norm [7:0] $end
$upscope $end
$scope module sensor_if $end
$var wire 8 [ arsenic_sensor [7:0] $end
$var wire 8 \ cadmium_sensor [7:0] $end
$var wire 8 ] chromium_sensor [7:0] $end
$var wire 1 % clk $end
$var wire 8 ^ lead_sensor [7:0] $end
$var wire 8 _ mercury_sensor [7:0] $end
$var wire 1 ( rst $end
$var reg 8 ` arsenic_data [7:0] $end
$var reg 8 a cadmium_data [7:0] $end
$var reg 8 b chromium_data [7:0] $end
$var reg 8 c lead_data [7:0] $end
$var reg 8 d mercury_data [7:0] $end
$upscope $end
$upscope $end
$upscope $end
$enddefinitions $end
$comment Show the parameter values. $end
$dumpall
b10110010 F
b1000011000 E
b101100101 D
b100001010 C
b110111110 B
b11111111111111001011110011000111 A
$end
#0
$dumpvars
b0 d
b0 c
b0 b
b0 a
b0 `
b0 _
b0 ^
b0 ]
b0 \
b0 [
b0 Z
b0 Y
b0 X
b0 W
b0 V
b0 U
b0 T
b0 S
b0 R
b0 Q
b0 P
b0 O
b0 N
b0 M
b0 L
b0 K
b0 J
b0 I
b0 H
b0 G
b0 @
b0 ?
b0 >
b0 =
b0 <
b0 ;
b0 :
b0 9
b0 8
b0 7
b0 6
b0 5
04
b0 3
b0 2
b0 1
b0 0
b0 /
b0 .
b0 -
b0 ,
b0 +
b0 *
b0 )
1(
b0 '
b0 &
0%
b0 $
b0 #
b0 "
0!
$end
#5000
1%
#10000
0%
#15000
1%
#20000
0%
b110 '
b110 -
b110 _
b111 $
b111 +
b111 ]
b101 #
b101 *
b101 \
b1000 "
b1000 )
b1000 [
b1010 &
b1010 ,
b1010 ^
0(
#25000
1!
14
b11111111111111001011110011000111 G
b110 0
b110 Q
b110 d
b111 6
b111 S
b111 b
b101 8
b101 T
b101 a
b1000 ;
b1000 U
b1000 `
b1010 3
b1010 R
b1010 c
1%
#30000
0%
#35000
b110 /
b110 <
b110 I
b110 Z
b111 5
b111 >
b111 K
b111 X
b101 7
b101 ?
b101 L
b101 W
b1000 :
b1000 @
b1000 M
b1000 V
b100100 H
b1010 2
b1010 =
b1010 J
b1010 Y
0!
04
1%
#40000
0%
#45000
b11111111111111001111001011001000 G
b1010 1
b1010 O
b111 9
b111 N
b100100 .
b100100 P
1%
#50000
0%
#55000
1%
#60000
0%
#65000
1%
#70000
0%
b10001100 '
b10001100 -
b10001100 _
b10100000 $
b10100000 +
b10100000 ]
b1111000 #
b1111000 *
b1111000 \
b10010110 "
b10010110 )
b10010110 [
b10110100 &
b10110100 ,
b10110100 ^
#75000
b10001100 0
b10001100 Q
b10001100 d
b10100000 6
b10100000 S
b10100000 b
b1111000 8
b1111000 T
b1111000 a
b10010110 ;
b10010110 U
b10010110 `
b10110100 3
b10110100 R
b10110100 c
1%
#80000
0%
#85000
b10001100 /
b10001100 <
b10001100 I
b10001100 Z
b10100000 5
b10100000 >
b10100000 K
b10100000 X
b1111000 7
b1111000 ?
b1111000 L
b1111000 W
b10010110 :
b10010110 @
b10010110 M
b10010110 V
b1011101110 H
b10110100 2
b10110100 =
b10110100 J
b10110100 Y
1%
#90000
0%
#95000
b10110100 1
b10110100 O
b10010110 9
b10010110 N
b1011101110 .
b1011101110 P
b1111100000100011 G
1%
#100000
0%
#105000
1!
14
1%
